miniwiki/__init__.py
miniwiki/__main__.py
miniwiki/app.py
miniwiki/auth.py
miniwiki/cache.py
miniwiki/config.py
miniwiki/models.py
miniwiki/util.py
miniwiki/templates/base.html
miniwiki/templates/edit_page.html
miniwiki/templates/error.html
miniwiki/templates/page.html
miniwiki/templates/page_history.html
miniwiki/templates/simple_login.html
miniwiki/templates/macro/index_links.html
miniwiki/templates/macro/page_meta.html
MiniWiki-0.7.dist-info/LICENSE.md
MiniWiki-0.7.dist-info/METADATA
MiniWiki-0.7.dist-info/WHEEL
MiniWiki-0.7.dist-info/entry_points.txt
MiniWiki-0.7.dist-info/top_level.txt
MiniWiki-0.7.dist-info/RECORD
