Metadata-Version: 2.1
Name: MiniWiki
Version: 0.7
Summary: UNKNOWN
Home-page: UNKNOWN
Author: Nick, Oxygem
Author-email: hello@oxygem.com
License: MIT
Platform: UNKNOWN
Requires-Python: >=3.6
Requires-Dist: cheroot (==8.3.0)
Requires-Dist: flask (==1.1.2)
Requires-Dist: flask-sqlalchemy (==2.4.3)
Requires-Dist: sqlalchemy (==1.3.7)
Requires-Dist: bcrypt (==3.1.7)
Requires-Dist: hashids (==1.2.0)
Requires-Dist: click (==7.1.2)
Requires-Dist: markdown (==2.6.9)
Requires-Dist: mdx-linkify (==1.0)
Provides-Extra: dev
Requires-Dist: wheel ; extra == 'dev'
Requires-Dist: twine ; extra == 'dev'
Provides-Extra: memcache
Requires-Dist: pymemcache (==3.2.0) ; extra == 'memcache'
